<?xml version="1.0" encoding="utf-8"?>
<LanguageData>
  <!--The following translations were generated by https://www.deepl.com/-->
  <CaveworldFlora.CannotGrowTooCold>Ne peut pas pousser maintenant : trop froid.</CaveworldFlora.CannotGrowTooCold>
  <CaveworldFlora.CannotGrowTooHot>Ne peut pas pousser maintenant : trop chaud.</CaveworldFlora.CannotGrowTooHot>
  <CaveworldFlora.Growing>En pleine croissance.</CaveworldFlora.Growing>
  <CaveworldFlora.MustOnRoughRock>Le bassin fongique doit être construit sur une roche brute.</CaveworldFlora.MustOnRoughRock>
  <CaveworldFlora.MustBeRoofed>Le bassin de fongicide doit être couvert.</CaveworldFlora.MustBeRoofed>
  <CaveworldFlora.TooClose>Un autre bassin de fungiponics est trop proche.</CaveworldFlora.TooClose>
  <CaveworldFlora.InCryostasis>En cryostase</CaveworldFlora.InCryostasis>
  <CaveworldFlora.Dying>Dying</CaveworldFlora.Dying>
  <CaveworldFlora.Drying>séchage</CaveworldFlora.Drying>
  <CaveworldFlora.TooDark>trop sombre</CaveworldFlora.TooDark>
  <CaveworldFlora.Overlit>superposé</CaveworldFlora.Overlit>
  <CaveworldFlora.Unroofed>sans toit</CaveworldFlora.Unroofed>
  <CaveworldFlora.UnadaptedSoil>sol non adapté</CaveworldFlora.UnadaptedSoil>
  <CaveworldFlora.TooFarFromRock>trop loin de la roche</CaveworldFlora.TooFarFromRock>
  <CaveworldFlora.ClusterRootRemoved>suppression de la racine du cluster</CaveworldFlora.ClusterRootRemoved>
  <CaveworldFlora.BrokenSymbiosis>symbiose brisée</CaveworldFlora.BrokenSymbiosis>
  <CaveworldFlora.Cryostasis>cryostase</CaveworldFlora.Cryostasis>
  <CaveworldFlora.LetterLabelBlackLotus>Lotus noir</CaveworldFlora.LetterLabelBlackLotus>
  <CaveworldFlora.BlackLotus>Un de vos colons a été intoxiqué par les effluves d'un lotus noir. Attention, ces émanations sont extrêmement toxiques.</CaveworldFlora.BlackLotus>
  <!-- Fungiponics Basin -->
  <!-- Flora Plant -->
  <!-- Black Lotus -->
</LanguageData>
